MANIFEST.in
README.md
README.txt
setup.py
aftermath/__init__.py
aftermath/app_settings.py
aftermath/runner.py
aftermath/backends/__init__.py
aftermath/backends/notify_send.py
aftermath/backends/null.py
django_aftermath.egg-info/PKG-INFO
django_aftermath.egg-info/SOURCES.txt
django_aftermath.egg-info/dependency_links.txt
django_aftermath.egg-info/not-zip-safe
django_aftermath.egg-info/top_level.txt