Metadata-Version: 1.1
Name: django-aftermath
Version: 0.1.0
Summary: Execute commands after tests are completed.
Home-page: https://github.com/amarsahinovic/django-aftermath
Author: Amar Šahinović
Author-email: amar@sahinovic.com
License: BSD License
Platform: UNKNOWN
Classifier: Environment :: Web Environment
Classifier: Framework :: Django
Classifier: Intended Audience :: Developers
Classifier: License :: OSI Approved :: BSD License
Classifier: Operating System :: OS Independent
Classifier: Programming Language :: Python
Classifier: Topic :: Utilities
